{
  "planet": {
    "name": { "value": "moon", "type": "other" },
    "label": { "value": "Moon", "type": "other" }
  },
  "color": {
    "background": {
      "base":    { "value": "#080808", "type": "color" },
      "subtle":  { "value": "#0e0e10", "type": "color" },
      "surface": { "value": "#141416", "type": "color" },
      "overlay": { "value": "#1e1e22", "type": "color" },
      "inverse": { "value": "#c8c8d0", "type": "color" }
    },
    "border": {
      "default": { "value": "rgba(140,140,150,0.14)", "type": "color" },
      "subtle":  { "value": "rgba(140,140,150,0.07)", "type": "color" },
      "strong":  { "value": "rgba(140,140,150,0.30)", "type": "color" },
      "focus":   { "value": "#8c8c96", "type": "color" }
    },
    "text": {
      "primary":   { "value": "#c8c8d0", "type": "color" },
      "secondary": { "value": "#8c8c96", "type": "color" },
      "muted":     { "value": "#484850", "type": "color" },
      "disabled":  { "value": "#28282e", "type": "color" },
      "inverse":   { "value": "#080808", "type": "color" },
      "accent":    { "value": "#a8a8b8", "type": "color" }
    },
    "action": {
      "primary":         { "value": "#8c8c96", "type": "color" },
      "primary-hover":   { "value": "#a4a4b0", "type": "color" },
      "primary-active":  { "value": "#70707a", "type": "color" },
      "secondary":       { "value": "rgba(140,140,150,0.14)", "type": "color" },
      "secondary-hover": { "value": "rgba(140,140,150,0.24)", "type": "color" }
    },
    "status": {
      "success": { "value": "#7090a8", "type": "color" },
      "warning": { "value": "#b0a068", "type": "color" },
      "error":   { "value": "#a06868", "type": "color" }
    }
  },
  "shadow": {
    "glow": { "value": "0 0 20px rgba(140,140,150,0.22)", "type": "boxShadow" }
  },
  "font": {
    "family": {
      "sans": { "value": "'Syne', system-ui, sans-serif", "type": "fontFamilies" }
    }
  },
  "radius": {
    "md": { "value": "2px", "type": "borderRadius" }
  }
}
