{
  "planet": {
    "name": { "value": "venus", "type": "other" },
    "label": { "value": "Venus", "type": "other" }
  },
  "color": {
    "background": {
      "base":    { "value": "#0f0d00", "type": "color" },
      "subtle":  { "value": "#141100", "type": "color" },
      "surface": { "value": "#1a1700", "type": "color" },
      "overlay": { "value": "#251f00", "type": "color" },
      "inverse": { "value": "#f5e8b0", "type": "color" }
    },
    "border": {
      "default": { "value": "rgba(220,185,60,0.14)", "type": "color" },
      "subtle":  { "value": "rgba(220,185,60,0.07)", "type": "color" },
      "strong":  { "value": "rgba(220,185,60,0.30)", "type": "color" },
      "focus":   { "value": "#e8c020", "type": "color" }
    },
    "text": {
      "primary":   { "value": "#f5e8b0", "type": "color" },
      "secondary": { "value": "#c4a84a", "type": "color" },
      "muted":     { "value": "#7a6420", "type": "color" },
      "disabled":  { "value": "#4a3c10", "type": "color" },
      "inverse":   { "value": "#0f0d00", "type": "color" },
      "accent":    { "value": "#e8c020", "type": "color" }
    },
    "action": {
      "primary":         { "value": "#e8c020", "type": "color" },
      "primary-hover":   { "value": "#f0cc30", "type": "color" },
      "primary-active":  { "value": "#c8a010", "type": "color" },
      "secondary":       { "value": "rgba(232,192,32,0.12)", "type": "color" },
      "secondary-hover": { "value": "rgba(232,192,32,0.20)", "type": "color" }
    },
    "status": {
      "success": { "value": "#8de87c", "type": "color" },
      "warning": { "value": "#e8a020", "type": "color" },
      "error":   { "value": "#e84040", "type": "color" }
    }
  },
  "shadow": {
    "glow": { "value": "0 0 20px rgba(232,192,32,0.30)", "type": "boxShadow" }
  },
  "font": {
    "family": {
      "sans": { "value": "'Noto Serif Display', 'Crimson Pro', serif", "type": "fontFamilies" }
    }
  },
  "radius": {
    "md": { "value": "0px", "type": "borderRadius" }
  }
}
